libOrbbecSDK.so
libOrbbecSDK.so.1.10
libOrbbecSDK.so.1.10.16
libdepthengine.so
libdepthengine.so.2.0
liblive555.so
libob_usb.so
pyorbbecsdk.cpython-310-x86_64-linux-gnu.so
sb_pyorbbecsdk-1.3.1.dist-info/licenses/LICENSE
sb_pyorbbecsdk-1.3.1.dist-info/METADATA
sb_pyorbbecsdk-1.3.1.dist-info/WHEEL
sb_pyorbbecsdk-1.3.1.dist-info/top_level.txt
sb_pyorbbecsdk-1.3.1.dist-info/RECORD
