Metadata-Version: 2.4
Name: sb-pyorbbecsdk
Version: 1.3.1
Summary: Python wrapper for the Orbbec 3D Camera SDK
Home-page: https://github.com/orbbec/pyorbbecsdk
Author: Joe Dong, Xiang Yang
Author-email: Joe Dong <mocun@orbbec.com>, Xiang Yang <yangxiang@baai.ac.cn>
Maintainer: Orbbec 3D Technology
Maintainer-email: support@orbbec.com
License: Apache-2.0
Project-URL: Homepage, https://github.com/orbbec/pyorbbecsdk
Project-URL: Repository, https://github.com/orbbec/pyorbbecsdk
Platform: Linux
Platform: Windows
Platform: macOS
Classifier: Development Status :: 4 - Beta
Classifier: Intended Audience :: Developers
Classifier: License :: OSI Approved :: Apache Software License
Classifier: Operating System :: POSIX :: Linux
Classifier: Programming Language :: Python :: 3
Classifier: Programming Language :: Python :: 3.8
Classifier: Programming Language :: Python :: 3.9
Classifier: Programming Language :: Python :: 3.10
Classifier: Programming Language :: Python :: 3.11
Classifier: Topic :: Scientific/Engineering
Requires-Python: >=3.8
License-File: LICENSE
Dynamic: author
Dynamic: home-page
Dynamic: license-file
Dynamic: maintainer
Dynamic: maintainer-email
Dynamic: platform
Dynamic: requires-python
